pew/__init__.py
pew/_print_utils.py
pew/_utils.py
pew/pew.py
pew/shell_config/_pew
pew/shell_config/complete.bash
pew/shell_config/complete.fish
pew/shell_config/complete.zsh
pew/shell_config/complete_deploy
pew/shell_config/init.bash
pew/shell_config/init.fish
pew/shell_config/init.zsh
pew_trobz-0.1.17.2.dist-info/METADATA
pew_trobz-0.1.17.2.dist-info/WHEEL
pew_trobz-0.1.17.2.dist-info/entry_points.txt
pew_trobz-0.1.17.2.dist-info/top_level.txt
pew_trobz-0.1.17.2.dist-info/RECORD
