Metadata-Version: 2.1
Name: pew-trobz
Version: 0.1.17.2
Summary: tool to manage multiple virtualenvs written in pure python, trobz's fork
Home-page: https://github.com/trobz/pew/tree/trobz
Author: Dario Bertini
Author-email: berdario+pypi@gmail.com
License: MIT License
Platform: UNKNOWN
Classifier: Programming Language :: Python :: 2
Classifier: Programming Language :: Python :: 3
Classifier: Intended Audience :: Developers
Classifier: Environment :: Console
Requires-Dist: virtualenv-trobz (>=16.7.10.1)
Requires-Dist: virtualenv-clone (>=0.2.5)
Requires-Dist: setuptools (>=17.1)
Requires-Dist: pythonz-trobz (>=1.10.4.1)
Requires-Dist: argparse ; python_version=="2.6"
Requires-Dist: pathlib ; python_version=="2.6"
Requires-Dist: backports.shutil-get-terminal-size ; python_version=="2.6"
Requires-Dist: shutilwhich ; python_version=="2.6"
Requires-Dist: pathlib ; python_version=="2.7"
Requires-Dist: backports.shutil-get-terminal-size ; python_version=="2.7"
Requires-Dist: shutilwhich ; python_version=="2.7"
Requires-Dist: pathlib ; python_version=="3.2"
Requires-Dist: backports.shutil-get-terminal-size ; python_version=="3.2"
Requires-Dist: shutilwhich ; python_version=="3.2"
Requires-Dist: pathlib ; python_version=="3.3"
